Keras_CoordConv/__init__.py
Keras_CoordConv/coord.py
Keras_CoordConv/coord_theano.py
Keras_CoordConv-0.6.dist-info/DESCRIPTION.rst
Keras_CoordConv-0.6.dist-info/METADATA
Keras_CoordConv-0.6.dist-info/RECORD
Keras_CoordConv-0.6.dist-info/WHEEL
Keras_CoordConv-0.6.dist-info/metadata.json
Keras_CoordConv-0.6.dist-info/top_level.txt
experiments/__init__.py
experiments/make_dataset.py
experiments/train_quadrant_classifier.py
experiments/train_uniform_classifier.py
