Metadata-Version: 2.0
Name: Keras-CoordConv
Version: 0.6
Summary: Keras implementation of CoordConv from the paper [An intriguing failing of convolutional neural networks and the CoordConv solution](https://arxiv.org/abs/1807.03247).
Home-page: UNKNOWN
Author: Ray Xu
Author-email: rxuniverse@google.com
License: UNKNOWN
Platform: UNKNOWN
Classifier: Programming Language :: Python :: 2
Classifier: License :: OSI Approved :: MIT License
Classifier: Operating System :: OS Independent
Requires-Dist: keras
